{"apiVersion":"ewm.sap.com/v1alpha1","items":[{"apiVersion":"ewm.sap.com/v1alpha1","kind":"RobotConfiguration","metadata":{"creationTimestamp":"2020-03-26T20:55:22Z","generation":7,"labels":{"cloudrobotics.com/robot-name":"freight93"},"name":"freight93","namespace":"default","resourceVersion":"39581304","selfLink":"/ewm-monitoring-ui/robotconfigurations/freight93","uid":"1c56fad5-6fa4-11ea-8fcc-42010a8400e1"},"rsrcgrp":"RBCD","rsrctype":"RB01","spec":{"batteryIdle":50,"batteryMin":10,"batteryOk":80,"chargers":["Charger1","Charger2","Charger3"],"lgnum":"1710","maxIdleTime":5,"recoverFromRobotError":false,"rsrcgrp":"RBCD","rsrctype":"RB01"},"status":{"lgnum":"","mission":"1585256165.269409","statemachine":"movingToStaging","subwho":"","tanum":"","who":""}},{"apiVersion":"ewm.sap.com/v1alpha1","kind":"RobotConfiguration","metadata":{"creationTimestamp":"2020-03-26T20:55:22Z","finalizers":["robot-gebhardt0.synced.cr-syncer.cloudrobotics.com"],"generation":2,"labels":{"cloudrobotics.com/robot-name":"gebhardt0"},"name":"gebhardt0","namespace":"default","resourceVersion":"46033302","selfLink":"/ewm-monitoring-ui/robotconfigurations/gebhardt0","uid":"1c583e14-6fa4-11ea-8fcc-42010a8400e1"},"spec":{"batteryIdle":40,"batteryMin":10,"batteryOk":80,"chargers":["Charger1","Charger2","Charger3"],"lgnum":"1710","maxIdleTime":5,"recoverFromRobotError":false,"rsrcgrp":"RBCD","rsrctype":"RB01"},"status":{"lgnum":"","mission":"1585911796.1151755","statemachine":"charging","subwho":"","tanum":"","who":""}},{"apiVersion":"ewm.sap.com/v1alpha1","kind":"RobotConfiguration","metadata":{"creationTimestamp":"2020-03-26T20:55:22Z","finalizers":["robot-mir-robot04.synced.cr-syncer.cloudrobotics.com"],"generation":4,"labels":{"cloudrobotics.com/robot-name":"mir-robot04"},"name":"mir-robot04","namespace":"default","resourceVersion":"49042955","selfLink":"/ewm-monitoring-ui/robotconfigurations/mir-robot04","uid":"1c59b817-6fa4-11ea-8fcc-42010a8400e1"},"spec":{"batteryIdle":40,"batteryMin":10,"batteryOk":80,"chargers":["Charger1","Charger2","Charger3"],"lgnum":"1710","maxIdleTime":5,"recoverFromRobotError":false,"rsrcgrp":"RBCD","rsrctype":"RB01"},"status":{"lgnum":"1710","mission":"1586166069.3655784","statemachine":"moveTrolley_movingToTargetBin","subwho":"","tanum":"100018574","who":"2018270"}},{"apiVersion":"ewm.sap.com/v1alpha1","kind":"RobotConfiguration","metadata":{"creationTimestamp":"2020-03-26T20:55:22Z","finalizers":["robot-mir-robot05.synced.cr-syncer.cloudrobotics.com"],"generation":8,"labels":{"cloudrobotics.com/robot-name":"mir-robot05"},"name":"mir-robot05","namespace":"default","resourceVersion":"49044109","selfLink":"/ewm-monitoring-ui/robotconfigurations/mir-robot05","uid":"1c5b4ef3-6fa4-11ea-8fcc-42010a8400e1"},"spec":{"batteryIdle":40,"batteryMin":10,"batteryOk":80,"chargers":["Charger1","Charger2","Charger3"],"lgnum":"1710","maxIdleTime":5,"recoverFromRobotError":false,"rsrcgrp":"RBCD","rsrctype":"RB01"},"status":{"lgnum":"1710","mission":"1586166167.1957755","statemachine":"moveTrolley_movingToTargetBin","subwho":"","tanum":"100018575","who":"2018271"}},{"apiVersion":"ewm.sap.com/v1alpha1","kind":"RobotConfiguration","metadata":{"creationTimestamp":"2020-03-26T20:55:22Z","finalizers":["robot-mir-robot06.synced.cr-syncer.cloudrobotics.com"],"generation":10,"labels":{"cloudrobotics.com/robot-name":"mir-robot06"},"name":"mir-robot06","namespace":"default","resourceVersion":"49030117","selfLink":"/ewm-monitoring-ui/robotconfigurations/mir-robot06","uid":"1c5cfedf-6fa4-11ea-8fcc-42010a8400e1"},"spec":{"batteryIdle":50,"batteryMin":10,"batteryOk":80,"chargers":["Charger1","Charger2","Charger3"],"lgnum":"1710","maxIdleTime":5,"recoverFromRobotError":false,"rsrcgrp":"RBCD","rsrctype":"RB01"},"status":{"lgnum":"","mission":"1586164986.251791","statemachine":"charging","subwho":"","tanum":"","who":""}}],"kind":"RobotConfigurationList","metadata":{"continue":"","resourceVersion":"49045346","selfLink":"/ewm-monitoring-ui/robotconfigurations/"}}